CHANGES
MANIFEST.in
README.rst
setup.py
src/django_detect_cyclic/__init__.py
src/django_detect_cyclic/apps_dependence.py
src/django_detect_cyclic/exceptions.py
src/django_detect_cyclic/forms.py
src/django_detect_cyclic/graph_utils.py
src/django_detect_cyclic/models.py
src/django_detect_cyclic/urls.py
src/django_detect_cyclic/utils.py
src/django_detect_cyclic/views.py
src/django_detect_cyclic.egg-info/PKG-INFO
src/django_detect_cyclic.egg-info/SOURCES.txt
src/django_detect_cyclic.egg-info/dependency_links.txt
src/django_detect_cyclic.egg-info/not-zip-safe
src/django_detect_cyclic.egg-info/requires.txt
src/django_detect_cyclic.egg-info/top_level.txt
src/django_detect_cyclic/locale/en/LC_MESSAGES/django.mo
src/django_detect_cyclic/locale/en/LC_MESSAGES/django.po
src/django_detect_cyclic/locale/es/LC_MESSAGES/django.mo
src/django_detect_cyclic/locale/es/LC_MESSAGES/django.po
src/django_detect_cyclic/management/__init__.py
src/django_detect_cyclic/management/commands/__init__.py
src/django_detect_cyclic/management/commands/detect_cyclic.py
src/django_detect_cyclic/static/css/jquery.graphviz.0.0.1.css
src/django_detect_cyclic/static/js/jquery-1.7.2.min.js
src/django_detect_cyclic/static/js/jquery-ui-1.8.21.min.js
src/django_detect_cyclic/static/js/jquery.graphviz.0.0.1.js
src/django_detect_cyclic/templates/detect_cyclic/detect_cyclic.html
src/django_detect_cyclic/templates/detect_cyclic/inc.svg_js_libraries.html