Metadata-Version: 1.0
Name: django-detect-cyclic
Version: 0.0.9
Summary: Django application to detect cyclic imports
Home-page: https://github.com/goinnn/django-detect-cyclic
Author: Pablo Martin
Author-email: goinnn@gmail.com
License: LGPL 3
Keywords: django,imports,cycle,cyclic imports,analyze code
Platform: UNKNOWN
Classifier: Development Status :: 4 - Beta
Classifier: Framework :: Django
Classifier: License :: OSI Approved :: GNU Library or Lesser General Public License (LGPL)
